iterator_cacher/__init__.py
iterator_cacher/iterator_cacher.py
iterator_cacher-1.0.4.dist-info/LICENSE.md
iterator_cacher-1.0.4.dist-info/METADATA
iterator_cacher-1.0.4.dist-info/WHEEL
iterator_cacher-1.0.4.dist-info/entry_points.txt
iterator_cacher-1.0.4.dist-info/top_level.txt
iterator_cacher-1.0.4.dist-info/RECORD
